ormysql/__init__.py
ormysql/base.py
ormysql/db.py
ormysql/fields.py
ormysql/migrate.py
ormysql/query.py
ormysql/relations.py
ormysql-0.1.5.dist-info/licenses/LICENSE
ormysql-0.1.5.dist-info/METADATA
ormysql-0.1.5.dist-info/WHEEL
ormysql-0.1.5.dist-info/top_level.txt
ormysql-0.1.5.dist-info/RECORD
