Metadata-Version: 2.4
Name: ormysql
Version: 0.1.5
Summary: MySQL ORM
Home-page: https://github.com/VsevolodKrasovskyi/mysql-orm-lite
Author: Vsevolod Krasovskyi
Author-email: sevakrasovskiy@gmail.com
License: MIT
Classifier: Development Status :: 4 - Beta
Classifier: Programming Language :: Python :: 3
Classifier: License :: OSI Approved :: MIT License
Classifier: Operating System :: OS Independent
Requires-Python: >=3.6
License-File: LICENSE
Requires-Dist: aiomysql
Dynamic: author
Dynamic: author-email
Dynamic: classifier
Dynamic: description
Dynamic: description-content-type
Dynamic: home-page
Dynamic: license
Dynamic: license-file
Dynamic: requires-dist
Dynamic: requires-python
Dynamic: summary
